[{"title":"The Time Machine","date":"2018-08-15T00:00:00.000Z","tags":["writings","book","reflection"],"draft":false,"summary":"The Time Traveller (for so it will be convenient to speak of him) was expounding a recondite matter to us. His pale grey eyes shone and twinkled, and his usually pale face was flushed and animated...","slug":"en/the-time-machine","type":"Blog","readingTime":{"text":"9 min read","minutes":8.53,"time":511800,"words":1706},"path":"blog/en/the-time-machine","filePath":"blog/en/the-time-machine.mdx","toc":[{"value":"The Time Machine by H. G. Wells","url":"#the-time-machine-by-h-g-wells","depth":1},{"value":"Introduction","url":"#introduction","depth":2}],"language":"the-time-machine.mdx","structuredData":{"@context":"https://schema.org","@type":"BlogPosting","headline":"The Time Machine","datePublished":"2018-08-15T00:00:00.000Z","dateModified":"2018-08-15T00:00:00.000Z","description":"The Time Traveller (for so it will be convenient to speak of him) was expounding a recondite matter to us. His pale grey eyes shone and twinkled, and his usually pale face was flushed and animated...","image":"/static/images/twitter-card.png","url":"https://tailwind-nextjs-starter-blog.vercel.app/blog/en/the-time-machine"}},{"title":"时间机器","date":"2018-08-15T00:00:00.000Z","tags":["writings","book","reflection"],"draft":false,"summary":"时间旅行者（为了方便起见，我们这样称呼他）正在向我们阐述一个深奥的问题。他灰白色的眼睛闪闪发光，通常苍白的脸色变得红润和生动……","slug":"zh/the-time-machine","translationOf":"the-time-machine\r","type":"Blog","readingTime":{"text":"14 min read","minutes":13.1,"time":786000,"words":2620},"path":"blog/zh/the-time-machine","filePath":"blog/zh/the-time-machine.mdx","toc":[{"value":"H. G. 威尔斯的《时间机器》","url":"#h-g-威尔斯的时间机器","depth":1},{"value":"引言","url":"#引言","depth":2}],"language":"the-time-machine.mdx","structuredData":{"@context":"https://schema.org","@type":"BlogPosting","headline":"时间机器","datePublished":"2018-08-15T00:00:00.000Z","dateModified":"2018-08-15T00:00:00.000Z","description":"时间旅行者（为了方便起见，我们这样称呼他）正在向我们阐述一个深奥的问题。他灰白色的眼睛闪闪发光，通常苍白的脸色变得红润和生动……","image":"/static/images/twitter-card.png","url":"https://tailwind-nextjs-starter-blog.vercel.app/blog/zh/the-time-machine"}}]